[{"timestamp":1651893895775,"files":[{"filename":"0.chunk.*****.js","previous":2916,"size":2916,"diff":0},{"filename":"bundle.*****.js","previous":6244,"size":6244,"diff":0},{"filename":"polyfills.*****.js","previous":2289,"size":2289,"diff":0},{"filename":"route-home.chunk.*****.js","previous":11917,"size":11917,"diff":0},{"filename":"bundle.3e80e.css","previous":198,"size":198,"diff":0},{"filename":"index.html","previous":558,"size":551,"diff":-7},{"filename":"route-home.chunk.02bea.css","previous":689,"size":689,"diff":0},{"filename":"30271d58bf7364c7ce9b.worker.js","previous":2640,"size":2640,"diff":0}]},{"timestamp":1651827348649,"files":[{"filename":"0.chunk.*****.js","previous":2917,"size":2916,"diff":-1},{"filename":"bundle.*****.js","previous":6245,"size":6244,"diff":-1},{"filename":"polyfills.*****.js","previous":2293,"size":2289,"diff":-4},{"filename":"route-home.chunk.*****.js","previous":11922,"size":11917,"diff":-5},{"filename":"12f7b70e55353f3fb72e.worker.js","previous":2640,"size":0,"diff":-2640},{"filename":"bundle.3e80e.css","previous":198,"size":198,"diff":0},{"filename":"index.html","previous":555,"size":558,"diff":3},{"filename":"route-home.chunk.02bea.css","previous":689,"size":689,"diff":0},{"filename":"30271d58bf7364c7ce9b.worker.js","previous":0,"size":2640,"diff":2640}]},{"timestamp":1651826751734,"files":[{"filename":"0.chunk.*****.js","previous":2917,"size":2917,"diff":0},{"filename":"bundle.*****.js","previous":5912,"size":6245,"diff":333},{"filename":"polyfills.*****.js","previous":2293,"size":2293,"diff":0},{"filename":"route-home.chunk.*****.js","previous":12090,"size":11922,"diff":-168},{"filename":"12f7b70e55353f3fb72e.worker.js","previous":2640,"size":2640,"diff":0},{"filename":"bundle.3e80e.css","previous":198,"size":198,"diff":0},{"filename":"route-home.chunk.ecb70.css","previous":677,"size":0,"diff":-677},{"filename":"index.html","previous":557,"size":555,"diff":-2},{"filename":"route-home.chunk.02bea.css","previous":0,"size":689,"diff":689}]},{"timestamp":1651812775387,"files":[{"filename":"0.chunk.*****.js","previous":2917,"size":2917,"diff":0},{"filename":"bundle.*****.js","previous":6003,"size":5912,"diff":-91},{"filename":"polyfills.*****.js","previous":2293,"size":2293,"diff":0},{"filename":"route-home.chunk.*****.js","previous":12474,"size":12090,"diff":-384},{"filename":"12f7b70e55353f3fb72e.worker.js","previous":2640,"size":2640,"diff":0},{"filename":"bundle.3e80e.css","previous":0,"size":198,"diff":198},{"filename":"route-home.chunk.ecb70.css","previous":0,"size":677,"diff":677},{"filename":"index.html","previous":0,"size":557,"diff":557}]},{"timestamp":1651807585170,"files":[{"filename":"dae46e3952072cf47d9e.worker.js","previous":2387,"size":0,"diff":-2387},{"filename":"0.chunk.*****.js","previous":2672,"size":2917,"diff":245},{"filename":"bundle.0af02.css","previous":195,"size":0,"diff":-195},{"filename":"bundle.*****.js","previous":5635,"size":6003,"diff":368},{"filename":"polyfills.*****.js","previous":2022,"size":2293,"diff":271},{"filename":"route-home.chunk.fe469.css","previous":682,"size":0,"diff":-682},{"filename":"route-home.chunk.*****.js","previous":11430,"size":12474,"diff":1044},{"filename":"12f7b70e55353f3fb72e.worker.js","previous":0,"size":2640,"diff":2640}]},{"timestamp":1588676616953,"files":[{"filename":"dae46e3952072cf47d9e.worker.js","previous":0,"size":2387,"diff":2387},{"filename":"0.chunk.*****.js","previous":0,"size":2672,"diff":2672},{"filename":"bundle.0af02.css","previous":0,"size":195,"diff":195},{"filename":"bundle.*****.js","previous":0,"size":5635,"diff":5635},{"filename":"polyfills.*****.js","previous":0,"size":2022,"diff":2022},{"filename":"route-home.chunk.fe469.css","previous":0,"size":682,"diff":682},{"filename":"route-home.chunk.*****.js","previous":0,"size":11430,"diff":11430}]}]
